nautobot_app_vpn/__init__.py
nautobot_app_vpn/api/__init__.py
nautobot_app_vpn/api/pagination.py
nautobot_app_vpn/api/permissions.py
nautobot_app_vpn/api/serializers.py
nautobot_app_vpn/api/urls.py
nautobot_app_vpn/api/viewsets.py
nautobot_app_vpn/filters.py
nautobot_app_vpn/forms/__init__.py
nautobot_app_vpn/forms/ikecrypto.py
nautobot_app_vpn/forms/ikegateway.py
nautobot_app_vpn/forms/ipseccrypto.py
nautobot_app_vpn/forms/ipsectunnel.py
nautobot_app_vpn/forms/tunnelmonitor.py
nautobot_app_vpn/jobs/__init__.py
nautobot_app_vpn/jobs/sync_neo4j_job.py
nautobot_app_vpn/migrations/0001_initial.py
nautobot_app_vpn/migrations/0002_auto_20250804_0411.py
nautobot_app_vpn/migrations/__init__.py
nautobot_app_vpn/models/__init__.py
nautobot_app_vpn/models/algorithms.py
nautobot_app_vpn/models/constants.py
nautobot_app_vpn/models/ikecrypto.py
nautobot_app_vpn/models/ikegateway.py
nautobot_app_vpn/models/ipseccrypto.py
nautobot_app_vpn/models/ipsectunnel.py
nautobot_app_vpn/models/tunnelmonitor.py
nautobot_app_vpn/models/vpn_dashboard.py
nautobot_app_vpn/navigation.py
nautobot_app_vpn/static/nautobot_app_vpn/css/dashboard_cytoscape.css
nautobot_app_vpn/static/nautobot_app_vpn/docs/404.html
nautobot_app_vpn/static/nautobot_app_vpn/docs/admin/compatibility_matrix/index.html
nautobot_app_vpn/static/nautobot_app_vpn/docs/admin/install/index.html
nautobot_app_vpn/static/nautobot_app_vpn/docs/admin/release_notes/index.html
nautobot_app_vpn/static/nautobot_app_vpn/docs/admin/release_notes/version_1.0/index.html
nautobot_app_vpn/static/nautobot_app_vpn/docs/admin/uninstall/index.html
nautobot_app_vpn/static/nautobot_app_vpn/docs/admin/upgrade/index.html
nautobot_app_vpn/static/nautobot_app_vpn/docs/assets/_mkdocstrings.css
nautobot_app_vpn/static/nautobot_app_vpn/docs/assets/extra.css
nautobot_app_vpn/static/nautobot_app_vpn/docs/assets/favicon.ico
nautobot_app_vpn/static/nautobot_app_vpn/docs/assets/images/favicon.png
nautobot_app_vpn-1.0.5.dist-info/LICENSE
nautobot_app_vpn-1.0.5.dist-info/METADATA
nautobot_app_vpn-1.0.5.dist-info/WHEEL
nautobot_app_vpn-1.0.5.dist-info/RECORD
