Metadata-Version: 2.3
Name: nautobot-app-vpn
Version: 1.0.5
Summary: VPN APP
License: Apache-2.0
Keywords: nautobot,nautobot-app,nautobot-plugin
Author: ISS World Services
Author-email: GITSO-Network@group.issworld.com
Requires-Python: >=3.11,<3.13
Classifier: Development Status :: 5 - Production/Stable
Classifier: Intended Audience :: Developers
Classifier: License :: OSI Approved :: Apache Software License
Classifier: Programming Language :: Python :: 3
Classifier: Programming Language :: Python :: 3.11
Classifier: Programming Language :: Python :: 3.12
Classifier: Programming Language :: Python :: 3.10
Classifier: Programming Language :: Python :: 3.8
Classifier: Programming Language :: Python :: 3.9
Provides-Extra: all
Requires-Dist: django (>=4.2,<5.0)
Requires-Dist: djangorestframework (>=3.15,<4.0)
Requires-Dist: nautobot (==2.4.10) ; python_version == "3.11"
Requires-Dist: neo4j (>=5.0,<6.0)
Project-URL: Documentation, https://github.com/iss-world/nautobot-app-vpn?tab=readme-ov-file#readme
Project-URL: Homepage, https://github.com/iss-world/nautobot-app-vpn
Project-URL: Repository, https://github.com/iss-world/nautobot-app-vpn
